scvi_criticism/__init__.py
scvi_criticism/_constants.py
scvi_criticism/_de_utils.py
scvi_criticism/_ppc.py
scvi_criticism/_ppc_plot.py
scvi_criticism/_settings.py
scvi_criticism/_utils.py
scvi_criticism-0.1.0.dist-info/METADATA
scvi_criticism-0.1.0.dist-info/WHEEL
scvi_criticism-0.1.0.dist-info/licenses/LICENSE
scvi_criticism-0.1.0.dist-info/RECORD
