Metadata-Version: 2.1
Name: scvi-criticism
Version: 0.1.0
Summary: Evaluation metrics for scvi-tools models
Project-URL: Documentation, https://scvi-criticism.readthedocs.io/
Project-URL: Source, https://github.com/YosefLab/scvi-criticism
Project-URL: Home-page, https://github.com/YosefLab/scvi-criticism
Author: Valeh Valiollah Pour Amiri
Maintainer-email: Valeh Valiollah Pour Amiri <valehvpa@berkeley.edu>
License: BSD 3-Clause License
License-File: LICENSE
Requires-Python: >=3.8
Requires-Dist: anndata
Requires-Dist: matplotlib
Requires-Dist: numpy
Requires-Dist: pandas
Requires-Dist: rich
Requires-Dist: scanpy
Requires-Dist: scipy
Requires-Dist: seaborn
Requires-Dist: session-info
Requires-Dist: sklearn
Provides-Extra: dev
Requires-Dist: bump2version; extra == 'dev'
Requires-Dist: pre-commit; extra == 'dev'
Requires-Dist: twine>=4.0.2; extra == 'dev'
Provides-Extra: doc
Requires-Dist: ipykernel; extra == 'doc'
Requires-Dist: ipython; extra == 'doc'
Requires-Dist: myst-nb; extra == 'doc'
Requires-Dist: sphinx-autodoc-typehints; extra == 'doc'
Requires-Dist: sphinx-book-theme>=0.3.3; extra == 'doc'
Requires-Dist: sphinx-copybutton; extra == 'doc'
Requires-Dist: sphinx>=4; extra == 'doc'
Requires-Dist: sphinxcontrib-bibtex>=1.0.0; extra == 'doc'
Provides-Extra: test
Requires-Dist: pytest; extra == 'test'
Requires-Dist: pytest-cov; extra == 'test'
Requires-Dist: scvi-tools; extra == 'test'
